livestatic/__init__.py
livestatic/config.py
livestatic/console.py
livestatic/serve.py
livestatic/urls.py
livestatic/webapp.py
livestatic/views/__init__.py
livestatic/views/exceptions.py
livestatic/views/responses.py
livestatic-0.0.6.dist-info/METADATA
livestatic-0.0.6.dist-info/WHEEL
livestatic-0.0.6.dist-info/licenses/LICENSE
livestatic-0.0.6.dist-info/RECORD
