Metadata-Version: 2.1
Name: livestatic
Version: 0.0.6
Summary: serve static page very easily
Project-URL: Homepage, https://github.com/ngdream/livestatic
Project-URL: Bug Tracker, https://github.com/ngdream/livestatic/issues
Author-email: ngdream <nguewofoss@gmail.com>
License: MIT License
Classifier: License :: OSI Approved :: MIT License
Classifier: Operating System :: OS Independent
Classifier: Programming Language :: Python :: 3
Requires-Python: >=3.7
